{
    "archive_path": "archive/1635283400.388175",
    "base_url": "danluu.com/look-stupid",
    "basename": "",
    "bookmarked_date": "2021-10-26 21:23",
    "canonical": {
        "archive_org_path": "https://web.archive.org/web/danluu.com/look-stupid",
        "dom_path": "output.html",
        "favicon_path": "favicon.ico",
        "git_path": "git/",
        "google_favicon_path": "https://www.google.com/s2/favicons?domain=danluu.com",
        "headers_path": "headers.json",
        "index_path": "index.html",
        "media_path": "media/",
        "mercury_path": "mercury/content.html",
        "pdf_path": "output.pdf",
        "readability_path": "readability/content.html",
        "screenshot_path": "screenshot.png",
        "singlefile_path": "singlefile.html",
        "warc_path": "warc/",
        "wget_path": null
    },
    "domain": "danluu.com",
    "extension": "",
    "hash": "D0NJ2QFNBCDBW8G7A849",
    "history": {
        "archive_org": [
            {
                "cmd": [
                    "curl",
                    "--silent",
                    "--location",
                    "--compressed",
                    "--head",
                    "--max-time",
                    "90",
                    "--user-agent",
                    "Mozilla/5.0 (Macintosh; Intel Mac OS X 10_15_7) AppleWebKit/537.36 (KHTML, like Gecko) Chrome/90.0.4430.61 Safari/537.36 ArchiveBox/0.6.2 (+https://github.com/ArchiveBox/ArchiveBox/) curl/curl 7.76.1 (x86_64-pc-linux-gnu)",
                    "https://web.archive.org/save/https://danluu.com/look-stupid/"
                ],
                "cmd_version": "curl 7.76.1 (x86_64-pc-linux-gnu)",
                "end_ts": "2021-10-26T21:24:19.935500+00:00",
                "index_texts": null,
                "output": "https://web.archive.org/web/20211026212415/https://danluu.com/look-stupid/",
                "pwd": "/home/wesleyac/code/notebook/data/archivebox/archive/1635283400.388175",
                "schema": "ArchiveResult",
                "start_ts": "2021-10-26T21:23:29.894226+00:00",
                "status": "succeeded"
            }
        ],
        "dom": [
            {
                "cmd": [
                    "chromium-browser",
                    "--headless",
                    "--user-agent=Mozilla/5.0 (Macintosh; Intel Mac OS X 10_15_7) AppleWebKit/537.36 (KHTML, like Gecko) Chrome/90.0.4430.61 Safari/537.36 ArchiveBox/{VERSION} (+https://github.com/ArchiveBox/ArchiveBox/)",
                    "--window-size=1440,2000",
                    "--timeout=90000",
                    "--dump-dom",
                    "https://danluu.com/look-stupid/"
                ],
                "cmd_version": "Chromium 93.0.4577.82",
                "end_ts": "2021-10-26T21:23:29.880898+00:00",
                "index_texts": null,
                "output": "output.html",
                "pwd": "/home/wesleyac/code/notebook/data/archivebox/archive/1635283400.388175",
                "schema": "ArchiveResult",
                "start_ts": "2021-10-26T21:23:29.335361+00:00",
                "status": "succeeded"
            }
        ],
        "favicon": [
            {
                "cmd": [
                    "curl",
                    "--silent",
                    "--location",
                    "--compressed",
                    "--max-time",
                    "90",
                    "--output",
                    "favicon.ico",
                    "--user-agent",
                    "Mozilla/5.0 (Macintosh; Intel Mac OS X 10_15_7) AppleWebKit/537.36 (KHTML, like Gecko) Chrome/90.0.4430.61 Safari/537.36 ArchiveBox/0.6.2 (+https://github.com/ArchiveBox/ArchiveBox/) curl/curl 7.76.1 (x86_64-pc-linux-gnu)",
                    "https://www.google.com/s2/favicons?domain=danluu.com"
                ],
                "cmd_version": "curl 7.76.1 (x86_64-pc-linux-gnu)",
                "end_ts": "2021-10-26T21:23:21.453001+00:00",
                "index_texts": null,
                "output": "favicon.ico",
                "pwd": "/home/wesleyac/code/notebook/data/archivebox/archive/1635283400.388175",
                "schema": "ArchiveResult",
                "start_ts": "2021-10-26T21:23:21.271055+00:00",
                "status": "succeeded"
            }
        ],
        "git": [],
        "headers": [
            {
                "cmd": [
                    "curl",
                    "--silent",
                    "--location",
                    "--compressed",
                    "--head",
                    "--max-time",
                    "90",
                    "--user-agent",
                    "Mozilla/5.0 (Macintosh; Intel Mac OS X 10_15_7) AppleWebKit/537.36 (KHTML, like Gecko) Chrome/90.0.4430.61 Safari/537.36 ArchiveBox/0.6.2 (+https://github.com/ArchiveBox/ArchiveBox/) curl/curl 7.76.1 (x86_64-pc-linux-gnu)",
                    "https://danluu.com/look-stupid/"
                ],
                "cmd_version": "curl 7.76.1 (x86_64-pc-linux-gnu)",
                "end_ts": "2021-10-26T21:23:21.701445+00:00",
                "index_texts": null,
                "output": "headers.json",
                "pwd": "/home/wesleyac/code/notebook/data/archivebox/archive/1635283400.388175",
                "schema": "ArchiveResult",
                "start_ts": "2021-10-26T21:23:21.482401+00:00",
                "status": "succeeded"
            }
        ],
        "media": [],
        "mercury": [],
        "pdf": [],
        "readability": [],
        "screenshot": [
            {
                "cmd": [
                    "chromium-browser",
                    "--headless",
                    "--user-agent=Mozilla/5.0 (Macintosh; Intel Mac OS X 10_15_7) AppleWebKit/537.36 (KHTML, like Gecko) Chrome/90.0.4430.61 Safari/537.36 ArchiveBox/{VERSION} (+https://github.com/ArchiveBox/ArchiveBox/)",
                    "--window-size=1440,2000",
                    "--timeout=90000",
                    "--screenshot",
                    "https://danluu.com/look-stupid/"
                ],
                "cmd_version": "Chromium 93.0.4577.82",
                "end_ts": "2021-10-26T21:23:29.321647+00:00",
                "index_texts": null,
                "output": "screenshot.png",
                "pwd": "/home/wesleyac/code/notebook/data/archivebox/archive/1635283400.388175",
                "schema": "ArchiveResult",
                "start_ts": "2021-10-26T21:23:28.187717+00:00",
                "status": "succeeded"
            }
        ],
        "singlefile": [
            {
                "cmd": [
                    "/home/wesleyac/code/notebook/data/archivebox/node_modules/single-file/cli/single-file",
                    "--browser-executable-path=chromium-browser",
                    "--browser-args=[\"--headless\", \"--user-agent=Mozilla/5.0 (Macintosh; Intel Mac OS X 10_15_7) AppleWebKit/537.36 (KHTML, like Gecko) Chrome/90.0.4430.61 Safari/537.36 ArchiveBox/{VERSION} (+https://github.com/ArchiveBox/ArchiveBox/)\", \"--window-size=1440,2000\"]",
                    "https://danluu.com/look-stupid/",
                    "singlefile.html"
                ],
                "cmd_version": "0.3.31",
                "end_ts": "2021-10-26T21:23:28.175162+00:00",
                "index_texts": null,
                "output": "singlefile.html",
                "pwd": "/home/wesleyac/code/notebook/data/archivebox/archive/1635283400.388175",
                "schema": "ArchiveResult",
                "start_ts": "2021-10-26T21:23:21.736206+00:00",
                "status": "succeeded"
            }
        ],
        "title": [
            {
                "cmd": [
                    "curl",
                    "--silent",
                    "--location",
                    "--compressed",
                    "--max-time",
                    "90",
                    "--user-agent",
                    "Mozilla/5.0 (Macintosh; Intel Mac OS X 10_15_7) AppleWebKit/537.36 (KHTML, like Gecko) Chrome/90.0.4430.61 Safari/537.36 ArchiveBox/0.6.2 (+https://github.com/ArchiveBox/ArchiveBox/) curl/curl 7.76.1 (x86_64-pc-linux-gnu)",
                    "https://danluu.com/look-stupid/"
                ],
                "cmd_version": "curl 7.76.1 (x86_64-pc-linux-gnu)",
                "end_ts": "2021-10-26T21:23:21.255071+00:00",
                "index_texts": null,
                "output": "Willingness to look stupid",
                "pwd": "/home/wesleyac/code/notebook/data/archivebox/archive/1635283400.388175",
                "schema": "ArchiveResult",
                "start_ts": "2021-10-26T21:23:20.898419+00:00",
                "status": "succeeded"
            }
        ],
        "wget": []
    },
    "icons": null,
    "is_archived": true,
    "is_static": false,
    "latest": {
        "archive_org": "https://web.archive.org/web/20211026212415/https://danluu.com/look-stupid/",
        "dom": "output.html",
        "favicon": "favicon.ico",
        "git": null,
        "media": null,
        "pdf": null,
        "screenshot": "screenshot.png",
        "singlefile": "singlefile.html",
        "title": "Willingness to look stupid",
        "warc": null,
        "wget": null
    },
    "link_dir": "/home/wesleyac/code/notebook/data/archivebox/archive/1635283400.388175",
    "newest_archive_date": "2021-10-26T21:23:29.894226+00:00",
    "num_failures": 0,
    "num_outputs": 7,
    "oldest_archive_date": "2021-10-26T21:23:20.898419+00:00",
    "path": "/look-stupid/",
    "schema": "Link",
    "scheme": "https",
    "snapshot_id": "40e1d1fc-f5f3-4246-9a28-13d3fb448004",
    "sources": [
        "/home/wesleyac/code/notebook/data/archivebox/sources/1635283400-import.txt"
    ],
    "tags": null,
    "tags_str": "",
    "timestamp": "1635283400.388175",
    "title": "Willingness to look stupid",
    "updated": "2021-10-26T21:23:20.894355+00:00",
    "updated_date": "2021-10-26 21:23",
    "url": "https://danluu.com/look-stupid/"
}