{
    "Status-Code": 200,
    "Connection": "keep-alive",
    "Content-Length": "14511",
    "Server": "nginx",
    "Content-Type": "text/html; charset=utf-8",
    "X-Content-Type-Options": "nosniff",
    "X-Drupal-Cache": "MISS",
    "Expires": "Sun, 19 Nov 1978 05:00:00 GMT",
    "Cache-Control": "public, max-age=1800",
    "Content-Security-Policy-Report-Only": "default-src https: 'unsafe-inline' 'unsafe-eval' 'self' data:; img-src 'self' *.eff.org data:; connect-src https: 'unsafe-inline' 'unsafe-eval' 'self' data: https://sentry.eff.org/api/2/store/; report-uri https://sentry.eff.org/api/2/security/?sentry_key=f1118ad37b5e4afbabe3487ca42fe73e",
    "X-Frame-Options": "SAMEORIGIN",
    "Content-Language": "en",
    "Permissions-Policy": "interest-cohort=()",
    "X-UA-Compatible": "IE=edge,chrome=1",
    "Link": "<https://www.eff.org/deeplinks/2017/03/payment-processors-are-still-policing-your-sex-life>; rel=\"canonical\",<https://www.eff.org/node/95201>; rel=\"shortlink\",<https://www.eff.org/>; rel=\"publisher\"",
    "Etag": "\"1644754206-1\"",
    "Last-Modified": "Sun, 13 Feb 2022 12:10:06 GMT",
    "Content-Encoding": "gzip",
    "Strict-Transport-Security": "max-age=63072000; includeSubdomains; preload",
    "X-XSS-Protection": "1; mode=block",
    "X-Download-Options": "noopen",
    "X-Permitted-Cross-Domain-Policies": "none",
    "Via": "1.1 varnish, 1.1 varnish",
    "Accept-Ranges": "bytes",
    "Date": "Sun, 13 Feb 2022 12:10:08 GMT",
    "Age": "1",
    "X-Served-By": "cache-sjc10027-SJC, cache-qpg1229-QPG",
    "X-Cache": "MISS, HIT",
    "X-Cache-Hits": "0, 1",
    "X-Timer": "S1644754208.416659,VS0,VE1",
    "Vary": "Cookie,fastly-ssl,Accept-Encoding"
}