{
    "Status-Code": 200,
    "Connection": "keep-alive",
    "Content-Length": "1810",
    "Server": "GitHub.com",
    "Content-Type": "text/html; charset=utf-8",
    "Last-Modified": "Sun, 20 Jun 2021 14:22:52 GMT",
    "Access-Control-Allow-Origin": "*",
    "ETag": "W/\"60cf4f3c-12ea\"",
    "expires": "Sun, 26 Sep 2021 22:27:37 GMT",
    "Cache-Control": "max-age=600",
    "Content-Encoding": "gzip",
    "x-proxy-cache": "MISS",
    "X-GitHub-Request-Id": "5BEA:6E9C:15B84B1:1FA3966:6150F181",
    "Accept-Ranges": "bytes",
    "Date": "Sun, 26 Sep 2021 22:17:38 GMT",
    "Via": "1.1 varnish",
    "Age": "0",
    "X-Served-By": "cache-lga21944-LGA",
    "X-Cache": "HIT",
    "X-Cache-Hits": "1",
    "X-Timer": "S1632694658.251087,VS0,VE1",
    "Vary": "Accept-Encoding",
    "X-Fastly-Request-ID": "296d1d926ad61d7e5e58a964905421ed79a3a9bc"
}