{
    "Status-Code": 200,
    "Server": "nginx",
    "Date": "Fri, 31 Dec 2021 09:23:39 GMT",
    "Content-Type": "text/html; charset=utf-8",
    "Content-Length": "16838",
    "Connection": "keep-alive",
    "X-Content-Type-Options": "nosniff",
    "Referrer-Policy": "same-origin",
    "X-Frame-Options": "DENY",
    "Vary": "Cookie",
    "Set-Cookie": "csrftoken=dbfTi8NLC53iHASk7gk3b5z32tswjim3G043hJxYgGz9OudNbfjjDmXCkJAHFPzX; expires=Fri, 30 Dec 2022 09:23:39 GMT; Max-Age=31449600; Path=/; SameSite=Lax"
}